ludus/__init__.py
ludus/cart_pole_cont.py
ludus/env.py
ludus/memory.py
ludus/policies.py
ludus/utils.py
ludus-0.1a3.dist-info/LICENSE
ludus-0.1a3.dist-info/METADATA
ludus-0.1a3.dist-info/WHEEL
ludus-0.1a3.dist-info/top_level.txt
ludus-0.1a3.dist-info/RECORD
