Metadata-Version: 2.1
Name: ludus
Version: 0.1a3
Summary: Reinforcement learning library to expediate application and research
Home-page: https://github.com/ejmejm/ludus
Author: Edan Meyer
Author-email: ejmejm98@gmail.com
License: UNKNOWN
Platform: UNKNOWN
Classifier: Programming Language :: Python :: 3
Classifier: License :: OSI Approved :: MIT License
Classifier: Operating System :: OS Independent
Requires-Dist: gym
Requires-Dist: opencv-python
Provides-Extra: atari
Requires-Dist: gym[atari] ; extra == 'atari'
Provides-Extra: tf
Requires-Dist: tensorflow (>=1.10) ; extra == 'tf'
Provides-Extra: tf-gpu
Requires-Dist: tensorflow-gpu (>=1.10) ; extra == 'tf-gpu'
